<?xml version="1.0"?>
<Root_Element X="0" Y="0" WIDTH="190" HEIGHT="215" MODAL="0" SHOWSID="3" HIDESID="4" DEFAULT_X="0" DEFAULT_Y="0" ADJUST_X="0" ADJUST_Y="0" DEFAULT_VISIBLE="0">
	<CAPTION ID="0" NAME="" X="0" Y="0" WIDTH="190" HEIGHT="20" />

    <IMAGE ID="0" NAME="" X="0" Y="0" WIDTH="23" HEIGHT="23" OFFSETX="0" OFFSETY="0" MODULEID="11" ALPHAVALUE="0" SCALEWIDTH="1" SCALEHEIGHT="1" GID="GEN_WND03_TL" SIZEFIT="0" />
	<IMAGE ID="0" NAME="" X="23" Y="0" WIDTH="144" HEIGHT="23" OFFSETX="0" OFFSETY="0" MODULEID="11" ALPHAVALUE="0" SCALEWIDTH="1" SCALEHEIGHT="1" GID="GEN_WND03_TC" SIZEFIT="1" />
	<IMAGE ID="0" NAME="" X="167" Y="0" WIDTH="23" HEIGHT="23" OFFSETX="0" OFFSETY="0" MODULEID="11" ALPHAVALUE="0" SCALEWIDTH="1" SCALEHEIGHT="1" GID="GEN_WND03_TR" SIZEFIT="0" />
	<IMAGE ID="0" NAME="" X="0" Y="23" WIDTH="23" HEIGHT="166" OFFSETX="0" OFFSETY="0" MODULEID="11" ALPHAVALUE="0" SCALEWIDTH="1" SCALEHEIGHT="1" GID="GEN_WND03_CL" SIZEFIT="1" />
	<IMAGE ID="0" NAME="" X="23" Y="23" WIDTH="144" HEIGHT="166" OFFSETX="0" OFFSETY="0" MODULEID="11" ALPHAVALUE="0" SCALEWIDTH="1" SCALEHEIGHT="1" GID="GEN_WND03_CC" SIZEFIT="1" />
	<IMAGE ID="0" NAME="" X="167" Y="23" WIDTH="23" HEIGHT="166" OFFSETX="0" OFFSETY="0" MODULEID="11" ALPHAVALUE="0" SCALEWIDTH="1" SCALEHEIGHT="1" GID="GEN_WND03_CR" SIZEFIT="1" />
	<IMAGE ID="0" NAME="" X="0" Y="189" WIDTH="23" HEIGHT="23" OFFSETX="0" OFFSETY="0" MODULEID="11" ALPHAVALUE="0" SCALEWIDTH="1" SCALEHEIGHT="1" GID="GEN_WND03_BL" SIZEFIT="0" />
	<IMAGE ID="0" NAME="" X="23" Y="189" WIDTH="144" HEIGHT="23" OFFSETX="0" OFFSETY="0" MODULEID="11" ALPHAVALUE="0" SCALEWIDTH="1" SCALEHEIGHT="1" GID="GEN_WND03_BC" SIZEFIT="1" />
	<IMAGE ID="0" NAME="" X="167" Y="189" WIDTH="23" HEIGHT="23" OFFSETX="0" OFFSETY="0" MODULEID="11" ALPHAVALUE="0" SCALEWIDTH="1" SCALEHEIGHT="1" GID="GEN_WND03_BR" SIZEFIT="0" />

	<RADIOBOX ID="37" NAME="" />
	<RADIOBUTTON ID="38" NAME="" X="20" Y="42" WIDTH="140" HEIGHT="16" OFFSETX="0" OFFSETY="0" RADIOBOXID="37" GHOST="0" MODULEID="11" DISABLESID="0" NORMALGID="GEN_DECO45" OVERGID="GEN_DECO47" DOWNGID="GEN_DECO46" />
	<RADIOBUTTON ID="39" NAME="" X="20" Y="59" WIDTH="140" HEIGHT="16" OFFSETX="0" OFFSETY="0" RADIOBOXID="37" GHOST="0" MODULEID="11" DISABLESID="0" NORMALGID="GEN_DECO45" OVERGID="GEN_DECO47" DOWNGID="GEN_DECO46" />

	<RADIOBOX ID="34" NAME="" />
	<RADIOBUTTON ID="35" NAME="" X="20" Y="104" WIDTH="140" HEIGHT="16" OFFSETX="0" OFFSETY="0" RADIOBOXID="34" GHOST="0" MODULEID="11" DISABLESID="0" NORMALGID="GEN_DECO45" OVERGID="GEN_DECO47" DOWNGID="GEN_DECO46" />
	<RADIOBUTTON ID="36" NAME="" X="20" Y="121" WIDTH="140" HEIGHT="16" OFFSETX="0" OFFSETY="0" RADIOBOXID="34" GHOST="0" MODULEID="11" DISABLESID="0" NORMALGID="GEN_DECO45" OVERGID="GEN_DECO47" DOWNGID="GEN_DECO46" />

	<CHECKBOX ID="40" NAME="" X="20" Y="150" WIDTH="140" HEIGHT="16" OFFSETX="0" OFFSETY="0" MODULEID="11" CHECKGID="GEN_DECO46" UNCHECKGID="GEN_DECO47" />

	<BUTTON ID="11" NAME="" X="20" Y="167" WIDTH="78" HEIGHT="32" OFFSETX="0" OFFSETY="0" MODULEID="11" NORMALGID="GEN_BTN15" OVERGID="GEN_BTN16" DOWNGID="GEN_BTN17" BLINKGID="" DISABLEGID="" OVERSID="0" CLICKSID="0" NOIMAGE="0" />
	<BUTTON ID="10" NAME="" X="91" Y="167" WIDTH="78" HEIGHT="32" OFFSETX="0" OFFSETY="0" MODULEID="11" NORMALGID="GEN_BTN15" OVERGID="GEN_BTN16" DOWNGID="GEN_BTN17" BLINKGID="" DISABLEGID="" OVERSID="0" CLICKSID="0" NOIMAGE="0" />

	<IMAGE ID="0" NAME="EXP_DISTRIBUTE" OFFSETX="0" OFFSETY="0" WIDTH="145" HEIGHT="16" X="25" Y="26" MODULEID="0" ALPHAVALUE="0" SCALEWIDTH="1" SCALEHEIGHT="1" GID="" HALIGN="0" VALIGN="4" FONT="110010" SIZEFIT="0" />
	<IMAGE ID="0" NAME="EXP_EQUALITY" OFFSETX="0" OFFSETY="0" WIDTH="145" HEIGHT="16" X="43" Y="42" MODULEID="0" ALPHAVALUE="0" SCALEWIDTH="1" SCALEHEIGHT="1" GID="" HALIGN="0" VALIGN="4" SIZEFIT="0" />
	<IMAGE ID="0" NAME="EXP_LEVELRATE" OFFSETX="0" OFFSETY="0" WIDTH="145" HEIGHT="16" X="43" Y="59" MODULEID="0" ALPHAVALUE="0" SCALEWIDTH="1" SCALEHEIGHT="1" GID="" HALIGN="0" VALIGN="4" SIZEFIT="0" />

	<IMAGE ID="0" NAME="PICKUP_RIGHT" OFFSETX="0" OFFSETY="0" WIDTH="145" HEIGHT="16" X="25" Y="88" MODULEID="0" ALPHAVALUE="0" SCALEWIDTH="1" SCALEHEIGHT="1" GID="" HALIGN="0" VALIGN="4" FONT="110010" SIZEFIT="0" />
	<IMAGE ID="0" NAME="PICKUP_RIGHT_ALL" OFFSETX="0" OFFSETY="0" WIDTH="145" HEIGHT="16" X="43" Y="104" MODULEID="0" ALPHAVALUE="0" SCALEWIDTH="1" SCALEHEIGHT="1" GID="" HALIGN="0" VALIGN="4" SIZEFIT="0" />
	<IMAGE ID="0" NAME="PICKUP_RIGHT_SEQENCE" OFFSETX="0" OFFSETY="0" WIDTH="145" HEIGHT="16" X="43" Y="121" MODULEID="0" ALPHAVALUE="0" SCALEWIDTH="1" SCALEHEIGHT="1" GID="" HALIGN="0" VALIGN="4" SIZEFIT="0" />

	<IMAGE ID="0" NAME="PARTY_HPGUAGE" OFFSETX="0" OFFSETY="0" WIDTH="145" HEIGHT="16" X="43" Y="150" MODULEID="0" ALPHAVALUE="0" SCALEWIDTH="1" SCALEHEIGHT="1" GID="" HALIGN="0" VALIGN="4" SIZEFIT="0" />
</Root_Element>